gitrack/__init__.py
gitrack/cli.py
gitrack/config.py
gitrack/exceptions.py
gitrack/helpers.py
gitrack/main.py
gitrack/prompt.py
gitrack/providers/__init__.py
gitrack/providers/toggl.py
gitrack/scripts/post_commit_executable_template.sh
gitrack/scripts/prompt_activate.clock.bash
gitrack/scripts/prompt_activate.clock.fish
gitrack/scripts/prompt_activate.simple.bash
gitrack/scripts/prompt_activate.simple.fish
gitrack/scripts/prompt_deactivate.bash
gitrack/scripts/prompt_deactivate.fish
gitrack-0.1.0.dist-info/AUTHORS
gitrack-0.1.0.dist-info/LICENSE
gitrack-0.1.0.dist-info/METADATA
gitrack-0.1.0.dist-info/WHEEL
gitrack-0.1.0.dist-info/entry_points.txt
gitrack-0.1.0.dist-info/pbr.json
gitrack-0.1.0.dist-info/top_level.txt
gitrack-0.1.0.dist-info/RECORD
