Metadata-Version: 2.1
Name: gitrack
Version: 0.1.0
Summary: Zero touch time tracking using Git
Home-page: https://github.com/AuHau/giTrack
Author: Adam Uhlir
Author-email: hello@adam-uhlir.me
License: MIT
Platform: UNKNOWN
Classifier: License :: OSI Approved :: MIT License
Classifier: Programming Language :: Python
Classifier: Programming Language :: Python :: 3
Classifier: Programming Language :: Python :: 3.5
Classifier: Programming Language :: Python :: 3.6
Classifier: Programming Language :: Python :: 3.7
Classifier: Programming Language :: Python :: Implementation :: CPython
Classifier: Development Status :: 4 - Beta
Classifier: Topic :: Office/Business :: Scheduling
Classifier: Intended Audience :: Developers
Requires-Python: >=3.5.0, <=3.7.*
Requires-Dist: gitpython (==2.1.11)
Requires-Dist: click (==7.0)
Requires-Dist: appdirs (==1.4.3)
Requires-Dist: togglCli (==2.0.2)
Requires-Dist: inquirer (==2.5.1)
Requires-Dist: click-completion (==0.5.0)
Requires-Dist: pbr (==5.1.1)
Requires-Dist: requests (==2.21.0)
